LICENSE
MANIFEST.in
README.rst
requirements.txt
setup.py
docs/Makefile
docs/source/conf.py
docs/source/index.rst
docs/source/manager.rst
docs/source/models.rst
src/bio2bel_hmdd/__init__.py
src/bio2bel_hmdd/__main__.py
src/bio2bel_hmdd/cli.py
src/bio2bel_hmdd/constants.py
src/bio2bel_hmdd/manager.py
src/bio2bel_hmdd/models.py
src/bio2bel_hmdd/parser.py
src/bio2bel_hmdd/web.py
src/bio2bel_hmdd.egg-info/PKG-INFO
src/bio2bel_hmdd.egg-info/SOURCES.txt
src/bio2bel_hmdd.egg-info/dependency_links.txt
src/bio2bel_hmdd.egg-info/entry_points.txt
src/bio2bel_hmdd.egg-info/requires.txt
src/bio2bel_hmdd.egg-info/top_level.txt