Metadata-Version: 1.0
Name: bio2bel-hmdd
Version: 0.0.1
Summary: A package for converting the Human microRNA Disease Database (HMDD) to BEL.
Home-page: https://github.com/bio2bel/hmdd
Author: Mehdi Ali, Dejan Dukic, and Charles Tapley Hoyt
Author-email: charles.hoyt@scai.fraunhofer.de
License: MIT License
Platform: UNKNOWN
